[
  {
    "id": "hotel26",
    "name": "Midtown Comfort JFK 1",
    "address": "26 W 45th Street, New York, NY 10036, USA",
    "city_code": "JFK",
    "stars": 3,
    "rating": 7.0,
    "amenities": [
      "Free Wi-Fi",
      "Restaurant",
      "Bar"
    ],
    "price_per_night": 120
  },
  {
    "id": "hotel27",
    "name": "Midtown Comfort JFK 2",
    "address": "27 W 45th Street, New York, NY 10036, USA",
    "city_code": "LAX",
    "stars": 4,
    "rating": 7.1,
    "amenities": [
      "Free Wi-Fi",
      "Fitness center",
      "Room service"
    ],
    "price_per_night": 130
  }
]